<?xml version="1.0" encoding="UTF-8" standalone="no"?>
<product_list>
    <product id="ASM_KM_0000" in_price="158633" in_stock="true" inventory_num="1455" name="Sơ Mi Nam KiriMaru Caro TD ST01" out_price="185000">
        <description/>
        <size id="M" inventory_num="670">
            <color id="LT" inventory_num="345" name="Lam Trắng">
                <shop id="shop_4" inventory_num="4"/>
                <shop id="shop_5" inventory_num="5"/>
                <shop id="shop_6" inventory_num="6"/>
                <shop id="shop_7" inventory_num="7"/>
                <shop id="shop_8" inventory_num="8"/>
                <shop id="shop_9" inventory_num="9"/>
                <shop id="shop_10" inventory_num="10"/>
                <shop id="shop_11" inventory_num="11"/>
                <shop id="shop_12" inventory_num="12"/>
                <shop id="shop_13" inventory_num="13"/>
                <shop id="shop_14" inventory_num="14"/>
                <shop id="shop_15" inventory_num="15"/>
                <shop id="shop_16" inventory_num="16"/>
                <shop id="shop_17" inventory_num="17"/>
                <shop id="shop_18" inventory_num="18"/>
                <shop id="shop_19" inventory_num="19"/>
                <shop id="shop_20" inventory_num="20"/>
                <shop id="shop_21" inventory_num="21"/>
                <shop id="shop_22" inventory_num="22"/>
                <shop id="shop_23" inventory_num="23"/>
                <shop id="shop_24" inventory_num="24"/>
                <shop id="shop_25" inventory_num="25"/>
                <shop id="shop_26" inventory_num="26"/>
            </color>
            <color id="DT" inventory_num="325" name="Đỏ Trắng">
                <shop id="shop_1" inventory_num="1"/>
                <shop id="shop_2" inventory_num="2"/>
                <shop id="shop_3" inventory_num="3"/>
                <shop id="shop_4" inventory_num="4"/>
                <shop id="shop_5" inventory_num="5"/>
                <shop id="shop_6" inventory_num="6"/>
                <shop id="shop_7" inventory_num="7"/>
                <shop id="shop_8" inventory_num="8"/>
                <shop id="shop_9" inventory_num="9"/>
                <shop id="shop_10" inventory_num="10"/>
                <shop id="shop_11" inventory_num="11"/>
                <shop id="shop_12" inventory_num="12"/>
                <shop id="shop_13" inventory_num="13"/>
                <shop id="shop_14" inventory_num="14"/>
                <shop id="shop_15" inventory_num="15"/>
                <shop id="shop_16" inventory_num="16"/>
                <shop id="shop_17" inventory_num="17"/>
                <shop id="shop_18" inventory_num="18"/>
                <shop id="shop_19" inventory_num="19"/>
                <shop id="shop_20" inventory_num="20"/>
                <shop id="shop_21" inventory_num="21"/>
                <shop id="shop_22" inventory_num="22"/>
                <shop id="shop_23" inventory_num="23"/>
                <shop id="shop_24" inventory_num="24"/>
                <shop id="shop_25" inventory_num="25"/>
            </color>
        </size>
        <size id="L" inventory_num="180">
            <color id="LT" inventory_num="140" name="Lam Trắng">
                <shop id="shop_17" inventory_num="17"/>
                <shop id="shop_18" inventory_num="18"/>
                <shop id="shop_19" inventory_num="19"/>
                <shop id="shop_20" inventory_num="20"/>
                <shop id="shop_21" inventory_num="21"/>
                <shop id="shop_22" inventory_num="22"/>
                <shop id="shop_23" inventory_num="23"/>
            </color>
            <color id="DT" inventory_num="40" name="Đỏ Trắng">
                <shop id="shop_6" inventory_num="6"/>
                <shop id="shop_7" inventory_num="7"/>
                <shop id="shop_8" inventory_num="8"/>
                <shop id="shop_9" inventory_num="9"/>
                <shop id="shop_10" inventory_num="10"/>
            </color>
        </size>
        <size id="XL" inventory_num="434">
            <color id="LT" inventory_num="259" name="Lam Trắng">
                <shop id="shop_12" inventory_num="12"/>
                <shop id="shop_13" inventory_num="13"/>
                <shop id="shop_14" inventory_num="14"/>
                <shop id="shop_15" inventory_num="15"/>
                <shop id="shop_16" inventory_num="16"/>
                <shop id="shop_17" inventory_num="17"/>
                <shop id="shop_18" inventory_num="18"/>
                <shop id="shop_19" inventory_num="19"/>
                <shop id="shop_20" inventory_num="20"/>
                <shop id="shop_21" inventory_num="21"/>
                <shop id="shop_22" inventory_num="22"/>
                <shop id="shop_23" inventory_num="23"/>
                <shop id="shop_24" inventory_num="24"/>
                <shop id="shop_25" inventory_num="25"/>
            </color>
            <color id="DT" inventory_num="175" name="Đỏ Trắng">
                <shop id="shop_22" inventory_num="22"/>
                <shop id="shop_23" inventory_num="23"/>
                <shop id="shop_24" inventory_num="24"/>
                <shop id="shop_25" inventory_num="25"/>
                <shop id="shop_26" inventory_num="26"/>
                <shop id="shop_27" inventory_num="27"/>
                <shop id="shop_28" inventory_num="28"/>
            </color>
        </size>
        <size id="XXL" inventory_num="171">
            <color id="LT" inventory_num="36" name="Lam Trắng">
                <shop id="shop_1" inventory_num="1"/>
                <shop id="shop_2" inventory_num="2"/>
                <shop id="shop_3" inventory_num="3"/>
                <shop id="shop_4" inventory_num="4"/>
                <shop id="shop_5" inventory_num="5"/>
                <shop id="shop_6" inventory_num="6"/>
                <shop id="shop_7" inventory_num="7"/>
                <shop id="shop_8" inventory_num="8"/>
            </color>
            <color id="DT" inventory_num="135" name="Đỏ Trắng">
                <shop id="shop_25" inventory_num="25"/>
                <shop id="shop_26" inventory_num="26"/>
                <shop id="shop_27" inventory_num="27"/>
                <shop id="shop_28" inventory_num="28"/>
                <shop id="shop_29" inventory_num="29"/>
            </color>
        </size>
    </product>
    <product id="ASM_KM_0001" in_price="118620" in_stock="true" inventory_num="494" name="Sơ Mi Nam KiriMaru TD C01" out_price="149000">
        <description>- Thiết kế áo sơ mi kiểu dáng basic. - Chất liệu Kate mềm mịn, thoáng mát. - Cotton chủ yếu trong thành phần sợi vải mang lại nhiều tính năng vượt trội: Thấm hút ẩm tốt, Không co rút,.. - Sử dụng công nghệ dệt may hiện đại hạn chế tối đa nhăn vải trong sử dụng. - Vải không nhuộm với chì an toàn cho sức khỏe, nhưng vẫn ít ra màu.</description>
        <size id="M" inventory_num="78">
            <color id="T" inventory_num="78" name="Trắng">
                <shop id="shop_25" inventory_num="25"/>
                <shop id="shop_26" inventory_num="26"/>
                <shop id="shop_27" inventory_num="27"/>
            </color>
        </size>
        <size id="L" inventory_num="1">
            <color id="T" inventory_num="1" name="Trắng">
                <shop id="shop_0" inventory_num="0"/>
                <shop id="shop_1" inventory_num="1"/>
            </color>
        </size>
        <size id="XL" inventory_num="126">
            <color id="T" inventory_num="126" name="Trắng">
                <shop id="shop_10" inventory_num="10"/>
                <shop id="shop_11" inventory_num="11"/>
                <shop id="shop_12" inventory_num="12"/>
                <shop id="shop_13" inventory_num="13"/>
                <shop id="shop_14" inventory_num="14"/>
                <shop id="shop_15" inventory_num="15"/>
                <shop id="shop_16" inventory_num="16"/>
                <shop id="shop_17" inventory_num="17"/>
                <shop id="shop_18" inventory_num="18"/>
            </color>
        </size>
        <size id="XXL" inventory_num="289">
            <color id="T" inventory_num="289" name="Trắng">
                <shop id="shop_9" inventory_num="9"/>
                <shop id="shop_10" inventory_num="10"/>
                <shop id="shop_11" inventory_num="11"/>
                <shop id="shop_12" inventory_num="12"/>
                <shop id="shop_13" inventory_num="13"/>
                <shop id="shop_14" inventory_num="14"/>
                <shop id="shop_15" inventory_num="15"/>
                <shop id="shop_16" inventory_num="16"/>
                <shop id="shop_17" inventory_num="17"/>
                <shop id="shop_18" inventory_num="18"/>
                <shop id="shop_19" inventory_num="19"/>
                <shop id="shop_20" inventory_num="20"/>
                <shop id="shop_21" inventory_num="21"/>
                <shop id="shop_22" inventory_num="22"/>
                <shop id="shop_23" inventory_num="23"/>
                <shop id="shop_24" inventory_num="24"/>
                <shop id="shop_25" inventory_num="25"/>
            </color>
        </size>
    </product>
    <product id="ASM_KM_0002" in_price="134303" in_stock="true" inventory_num="1759" name="Sơ Mi Nam KiriMaru Caro TN ST01" out_price="169000">
        <description>SƠ MI CARO - Thiết kế với kiểu dáng đơn giản, phong cách hiện đại với túi áo kiểu cách. - Chất liệu Kate với nhiều tính năng vượt trội: Thấm hút ẩm tốt, không co rút,.. - Sử dụng công nghệ dệt may hiện đại hạn chế tối đa nhăn vải trong sử dụng. - Vải không nhuộm với chì an toàn cho sức khỏe, nhưng vẫn ít ra màu.</description>
        <size id="M" inventory_num="288">
            <color id="D" inventory_num="147" name="Đỏ">
                <shop id="shop_4" inventory_num="4"/>
                <shop id="shop_5" inventory_num="5"/>
                <shop id="shop_6" inventory_num="6"/>
                <shop id="shop_7" inventory_num="7"/>
                <shop id="shop_8" inventory_num="8"/>
                <shop id="shop_9" inventory_num="9"/>
                <shop id="shop_10" inventory_num="10"/>
                <shop id="shop_11" inventory_num="11"/>
                <shop id="shop_12" inventory_num="12"/>
                <shop id="shop_13" inventory_num="13"/>
                <shop id="shop_14" inventory_num="14"/>
                <shop id="shop_15" inventory_num="15"/>
                <shop id="shop_16" inventory_num="16"/>
                <shop id="shop_17" inventory_num="17"/>
            </color>
            <color id="XL" inventory_num="141" name="Xanh Lá">
                <shop id="shop_21" inventory_num="21"/>
                <shop id="shop_22" inventory_num="22"/>
                <shop id="shop_23" inventory_num="23"/>
                <shop id="shop_24" inventory_num="24"/>
                <shop id="shop_25" inventory_num="25"/>
                <shop id="shop_26" inventory_num="26"/>
            </color>
        </size>
        <size id="L" inventory_num="350">
            <color id="D" inventory_num="322" name="Đỏ">
                <shop id="shop_3" inventory_num="3"/>
                <shop id="shop_4" inventory_num="4"/>
                <shop id="shop_5" inventory_num="5"/>
                <shop id="shop_6" inventory_num="6"/>
                <shop id="shop_7" inventory_num="7"/>
                <shop id="shop_8" inventory_num="8"/>
                <shop id="shop_9" inventory_num="9"/>
                <shop id="shop_10" inventory_num="10"/>
                <shop id="shop_11" inventory_num="11"/>
                <shop id="shop_12" inventory_num="12"/>
                <shop id="shop_13" inventory_num="13"/>
                <shop id="shop_14" inventory_num="14"/>
                <shop id="shop_15" inventory_num="15"/>
                <shop id="shop_16" inventory_num="16"/>
                <shop id="shop_17" inventory_num="17"/>
                <shop id="shop_18" inventory_num="18"/>
                <shop id="shop_19" inventory_num="19"/>
                <shop id="shop_20" inventory_num="20"/>
                <shop id="shop_21" inventory_num="21"/>
                <shop id="shop_22" inventory_num="22"/>
                <shop id="shop_23" inventory_num="23"/>
                <shop id="shop_24" inventory_num="24"/>
                <shop id="shop_25" inventory_num="25"/>
            </color>
            <color id="XL" inventory_num="28" name="Xanh Lá">
                <shop id="shop_1" inventory_num="1"/>
                <shop id="shop_2" inventory_num="2"/>
                <shop id="shop_3" inventory_num="3"/>
                <shop id="shop_4" inventory_num="4"/>
                <shop id="shop_5" inventory_num="5"/>
                <shop id="shop_6" inventory_num="6"/>
                <shop id="shop_7" inventory_num="7"/>
            </color>
        </size>
        <size id="XL" inventory_num="640">
            <color id="D" inventory_num="315" name="Đỏ">
                <shop id="shop_9" inventory_num="9"/>
                <shop id="shop_10" inventory_num="10"/>
                <shop id="shop_11" inventory_num="11"/>
                <shop id="shop_12" inventory_num="12"/>
                <shop id="shop_13" inventory_num="13"/>
                <shop id="shop_14" inventory_num="14"/>
                <shop id="shop_15" inventory_num="15"/>
                <shop id="shop_16" inventory_num="16"/>
                <shop id="shop_17" inventory_num="17"/>
                <shop id="shop_18" inventory_num="18"/>
                <shop id="shop_19" inventory_num="19"/>
                <shop id="shop_20" inventory_num="20"/>
                <shop id="shop_21" inventory_num="21"/>
                <shop id="shop_22" inventory_num="22"/>
                <shop id="shop_23" inventory_num="23"/>
                <shop id="shop_24" inventory_num="24"/>
                <shop id="shop_25" inventory_num="25"/>
                <shop id="shop_26" inventory_num="26"/>
            </color>
            <color id="XL" inventory_num="325" name="Xanh Lá">
                <shop id="shop_0" inventory_num="0"/>
                <shop id="shop_1" inventory_num="1"/>
                <shop id="shop_2" inventory_num="2"/>
                <shop id="shop_3" inventory_num="3"/>
                <shop id="shop_4" inventory_num="4"/>
                <shop id="shop_5" inventory_num="5"/>
                <shop id="shop_6" inventory_num="6"/>
                <shop id="shop_7" inventory_num="7"/>
                <shop id="shop_8" inventory_num="8"/>
                <shop id="shop_9" inventory_num="9"/>
                <shop id="shop_10" inventory_num="10"/>
                <shop id="shop_11" inventory_num="11"/>
                <shop id="shop_12" inventory_num="12"/>
                <shop id="shop_13" inventory_num="13"/>
                <shop id="shop_14" inventory_num="14"/>
                <shop id="shop_15" inventory_num="15"/>
                <shop id="shop_16" inventory_num="16"/>
                <shop id="shop_17" inventory_num="17"/>
                <shop id="shop_18" inventory_num="18"/>
                <shop id="shop_19" inventory_num="19"/>
                <shop id="shop_20" inventory_num="20"/>
                <shop id="shop_21" inventory_num="21"/>
                <shop id="shop_22" inventory_num="22"/>
                <shop id="shop_23" inventory_num="23"/>
                <shop id="shop_24" inventory_num="24"/>
                <shop id="shop_25" inventory_num="25"/>
            </color>
        </size>
        <size id="XXL" inventory_num="481">
            <color id="D" inventory_num="75" name="Đỏ">
                <shop id="shop_24" inventory_num="24"/>
                <shop id="shop_25" inventory_num="25"/>
                <shop id="shop_26" inventory_num="26"/>
            </color>
            <color id="XL" inventory_num="406" name="Xanh Lá">
                <shop id="shop_1" inventory_num="1"/>
                <shop id="shop_2" inventory_num="2"/>
                <shop id="shop_3" inventory_num="3"/>
                <shop id="shop_4" inventory_num="4"/>
                <shop id="shop_5" inventory_num="5"/>
                <shop id="shop_6" inventory_num="6"/>
                <shop id="shop_7" inventory_num="7"/>
                <shop id="shop_8" inventory_num="8"/>
                <shop id="shop_9" inventory_num="9"/>
                <shop id="shop_10" inventory_num="10"/>
                <shop id="shop_11" inventory_num="11"/>
                <shop id="shop_12" inventory_num="12"/>
                <shop id="shop_13" inventory_num="13"/>
                <shop id="shop_14" inventory_num="14"/>
                <shop id="shop_15" inventory_num="15"/>
                <shop id="shop_16" inventory_num="16"/>
                <shop id="shop_17" inventory_num="17"/>
                <shop id="shop_18" inventory_num="18"/>
                <shop id="shop_19" inventory_num="19"/>
                <shop id="shop_20" inventory_num="20"/>
                <shop id="shop_21" inventory_num="21"/>
                <shop id="shop_22" inventory_num="22"/>
                <shop id="shop_23" inventory_num="23"/>
                <shop id="shop_24" inventory_num="24"/>
                <shop id="shop_25" inventory_num="25"/>
                <shop id="shop_26" inventory_num="26"/>
                <shop id="shop_27" inventory_num="27"/>
                <shop id="shop_28" inventory_num="28"/>
            </color>
        </size>
    </product>
</product_list>